{
  "todos": [
    {
      "title": "Do something",
      "completed": true,
      "favorite": false,
      "id": 41
    },
    {
      "title": "Do something",
      "completed": false,
      "favorite": true,
      "id": 42
    },
    {
      "title": "Do something",
      "completed": false,
      "favorite": true,
      "id": 43
    },
    {
      "title": "Do something",
      "completed": false,
      "favorite": true,
      "id": 44
    },
    {
      "title": "Do something",
      "completed": false,
      "favorite": false,
      "id": 45
    },
    {
      "title": "Do something",
      "completed": false,
      "favorite": false,
      "id": 46
    }
  ]
}